Metadata-Version: 1.1
Name: indiesquare
Version: 0.0.2
Summary: IndieSquare API Library for Python
Home-page: https://github.com/kmn/indiesquare
Author: Shohei Kamon
Author-email: kamonshohei@gmail.com
License: MIT
Platform: UNKNOWN
Classifier: Development Status :: 5 - Production/Stable
Classifier: Intended Audience :: Developers
Classifier: Natural Language :: English
Classifier: License :: OSI Approved :: MIT License
Classifier: Programming Language :: Python
Classifier: Programming Language :: Python :: 3
Classifier: Programming Language :: Python :: 3.3
Classifier: Programming Language :: Python :: 3.4
Classifier: Programming Language :: Python :: 3.5
